{
  "sourceWidth": 512.0,
  "sourceHeight": 512.0,
  "vertices": [
    {
      "x": 9.04,
      "y": 273.68
    },
    {
      "x": 253.31,
      "y": 272.78
    },
    {
      "x": 253.44,
      "y": 442.27
    },
    {
      "x": 297.67,
      "y": 438.15
    },
    {
      "x": 316.91,
      "y": 380.73
    },
    {
      "x": 393.83,
      "y": 386.5
    },
    {
      "x": 412.24,
      "y": 401.34
    },
    {
      "x": 420.48,
      "y": 444.74
    },
    {
      "x": 484.21,
      "y": 447.49
    },
    {
      "x": 482.89,
      "y": 256.0
    },
    {
      "x": 451.0,
      "y": 231.47
    },
    {
      "x": 486.15,
      "y": 166.39
    },
    {
      "x": 482.89,
      "y": 105.87
    },
    {
      "x": 451.65,
      "y": 68.78
    },
    {
      "x": 390.48,
      "y": 57.71
    },
    {
      "x": 327.36,
      "y": 100.01
    },
    {
      "x": 307.18,
      "y": 162.49
    },
    {
      "x": 327.36,
      "y": 218.46
    },
    {
      "x": 166.615,
      "y": 216.83
    },
    {
      "x": 5.87,
      "y": 215.2
    }
  ],
  "qa": {
    "vertexCount": 20,
    "minEdgeWorld": 5.6751,
    "reflexRatio": 0.35,
    "selfIntersection": 0,
    "bbox": {
      "minX": 5.87,
      "minY": 57.71,
      "maxX": 486.15,
      "maxY": 447.49
    },
    "area": 81811.555,
    "maxConsecutiveSharp": 0,
    "thresholds": {
      "minEdgeWorld": 1.0,
      "maxReflexRatio": 0.55,
      "maxVertices": 96,
      "maxConsecutiveSharp": 6,
      "sharpAngleDeg": 55.0,
      "selfIntersection": 0
    }
  }
}
